{
  "title": "Nadzu API - Worker Health",
  "timezone": "browser",
  "refresh": "5s",
  "schemaVersion": 39,
  "panels": [
    {
      "title": "Current Success Rate",
      "type": "stat",
      "gridPos": { "h": 6, "w": 8, "x": 0, "y": 0 },
      "targets": [
        {
          "datasource": "Prometheus",
          "expr": "(((sum(ytdlp_jobs_completed_total{status=\"success\"}) or vector(0)) / (sum(ytdlp_jobs_completed_total) > 0)) * 100) or vector(100)",
          "legendFormat": "Success Rate"
        }
      ],
      "fieldConfig": {
        "defaults": {
          "unit": "percent",
          "noValue": 100,
          "thresholds": {
            "mode": "absolute",
            "steps": [
              { "color": "red", "value": null },
              { "color": "orange", "value": 80 },
              { "color": "green", "value": 95 }
            ]
          }
        }
      }
    },
    {
      "title": "Active Workers (Saturation)",
      "type": "gauge",
      "gridPos": { "h": 6, "w": 8, "x": 8, "y": 0 },
      "targets": [
        {
          "datasource": "Prometheus",
          "expr": "ytdlp_active_jobs"
        }
      ],
      "fieldConfig": {
        "defaults": {
          "min": 0,
          "max": 10,
          "thresholds": {
            "mode": "absolute",
            "steps": [
              { "color": "green", "value": null },
              { "color": "orange", "value": 5 },
              { "color": "red", "value": 8 }
            ]
          }
        }
      }
    },
    {
      "title": "Recent Error Count (1h)",
      "type": "stat",
      "gridPos": { "h": 6, "w": 8, "x": 16, "y": 0 },
      "targets": [
        {
          "datasource": "Prometheus",
          "expr": "sum(increase(ytdlp_jobs_completed_total{status=\"error\"}[1h]))"
        }
      ],
      "fieldConfig": {
        "defaults": {
          "color": { "mode": "thresholds" },
          "thresholds": {
            "mode": "absolute",
            "steps": [
              { "color": "green", "value": null },
              { "color": "red", "value": 1 }
            ]
          }
        }
      }
    },
    {
      "title": "Traffic Volume (Success vs Error)",
      "type": "timeseries",
      "gridPos": { "h": 9, "w": 24, "x": 0, "y": 6 },
      "targets": [
        {
          "datasource": "Prometheus",
          "expr": "sum by (status) (rate(ytdlp_jobs_completed_total[5m]))",
          "legendFormat": "{{status}}"
        }
      ],
      "fieldConfig": {
        "defaults": {
          "custom": {
            "drawStyle": "line",
            "fillOpacity": 20,
            "lineInterpolation": "smooth",
            "stacking": { "group": "A", "mode": "normal" }
          }
        },
        "overrides": [
          {
            "matcher": { "id": "byName", "options": "success" },
            "properties": [{ "id": "color", "value": { "fixedColor": "green", "mode": "fixed" } }]
          },
          {
            "matcher": { "id": "byName", "options": "error" },
            "properties": [{ "id": "color", "value": { "fixedColor": "red", "mode": "fixed" } }]
          }
        ]
      }
    },
    {
      "title": "Processing Latency (P50 vs P99)",
      "type": "timeseries",
      "gridPos": { "h": 9, "w": 24, "x": 0, "y": 15 },
      "targets": [
        {
          "datasource": "Prometheus",
          "expr": "ytdlp_job_duration_seconds{quantile=\"0.5\"}",
          "legendFormat": "P50 (Median)"
        },
        {
          "datasource": "Prometheus",
          "expr": "ytdlp_job_duration_seconds{quantile=\"0.99\"}",
          "legendFormat": "P99 (Worst Case)"
        }
      ],
      "fieldConfig": {
        "defaults": {
          "unit": "s",
          "custom": { "lineInterpolation": "smooth" }
        }
      }
    }
  ]
}